raghu/main.py
raghu2-2.0.0.dist-info/LICENSE
raghu2-2.0.0.dist-info/METADATA
raghu2-2.0.0.dist-info/WHEEL
raghu2-2.0.0.dist-info/entry_points.txt
raghu2-2.0.0.dist-info/top_level.txt
raghu2-2.0.0.dist-info/RECORD
