Metadata-Version: 2.1
Name: raghu2
Version: 2.0.0
Summary: A Python package to test in local
Home-page: https://github.com/Raghu960/raghu
Author: Raghavendra Deshmukh
Author-email: raghu.deshmukh55@gmail.com
License: MIT
Platform: UNKNOWN
Classifier: License :: OSI Approved :: MIT License
Classifier: Programming Language :: Python :: 3
Classifier: Programming Language :: Python :: 3.7
